<?xml version="1.0" encoding="UTF-8"?>
<objects serializationModel="Studio.02.02.00">
	<object class="Workspace" id="{e5874405-0063-4e1f-9b4f-8a78b857b44b}">
		<relationship name="projectSettings">
			<destination>{99336242-417f-4cd5-a635-c6f7aeffceea}</destination>
		</relationship>
		<relationship name="changelist">
			<destination>{289ce04c-89a1-45bc-a15c-60c23a5fdbd1}</destination>
		</relationship>
	</object>
	<object class="ProjectSettings" id="{99336242-417f-4cd5-a635-c6f7aeffceea}">
		<relationship name="activePlatform">
			<destination>{910049ea-ed11-4e40-ba65-32adcb514672}</destination>
		</relationship>
	</object>
	<object class="WorkspaceChangelist" id="{289ce04c-89a1-45bc-a15c-60c23a5fdbd1}" />
</objects>
