<?xml version="1.0" encoding="UTF-8"?>
<objects serializationModel="Studio.02.02.00">
	<object class="AudioFile" id="{46b4e46e-2fb4-4068-82e5-22ae889d7b38}">
		<property name="assetPath">
			<value>Characters/MainChar/FemaleIdle2.wav</value>
		</property>
		<property name="frequencyInKHz">
			<value>48</value>
		</property>
		<property name="channelCount">
			<value>1</value>
		</property>
		<property name="length">
			<value>0.86987499999999995</value>
		</property>
		<relationship name="masterAssetFolder">
			<destination>{2dfded11-f080-49ba-a389-508e2d65dd80}</destination>
		</relationship>
	</object>
</objects>
